ucdp_glbl-1.5.0.dist-info/METADATA
ucdp_glbl-1.5.0.dist-info/WHEEL
ucdp_glbl-1.5.0.dist-info/entry_points.txt
ucdp_glbl-1.5.0.dist-info/licenses/LICENSE
ucdp_glbl/__init__.py
ucdp_glbl/attrs.py
ucdp_glbl/dft.py
ucdp_glbl/finder.py
ucdp_glbl/irq.py
ucdp_glbl/lane.py
ucdp_glbl/mem.py
ucdp_glbl/stream.py
ucdp_glbl-1.5.0.dist-info/RECORD
