Metadata-Version: 2.1
Name: ucdp-glbl
Version: 1.5.0
Summary: Unified Chip Design Platform - Global
Classifier: Programming Language :: Python :: 3
Classifier: Operating System :: OS Independent
Project-URL: Homepage, https://github.com/nbiotcloud/ucdp-glbl
Project-URL: Documentation, https://ucdp-glbl.readthedocs.io/en/stable/
Project-URL: Bug Tracker, https://github.com/nbiotcloud/ucdp-glbl/issues
Requires-Python: <4.0,>=3.10.0
Requires-Dist: ucdp>=0.16.0
